gw_couch_database/__init__.py
gw_couch_database/database.py
gw_couch_database-0.5.0.dist-info/METADATA
gw_couch_database-0.5.0.dist-info/WHEEL
gw_couch_database-0.5.0.dist-info/RECORD
