Metadata-Version: 2.3
Name: gw-couch-database
Version: 0.5.0
Summary: Couch DB Functinality for GW Projects
Author: Chris Moore
Author-email: cmoore@guidewire.com
Requires-Python: >=3.13
Classifier: Programming Language :: Python :: 3
Classifier: Programming Language :: Python :: 3.13
Requires-Dist: couchdb3 (>=1.3.0,<2.0.0)
Requires-Dist: gw-settings-management (>=0.5.0,<0.6.0)
